sgb/__init__.py
sgb/collections/__init__.py
sgb/consts/__init__.py
sgb/consts/ad.py
sgb/consts/addresses.py
sgb/consts/argument.py
sgb/consts/community.py
sgb/consts/date_time.py
sgb/consts/errors.py
sgb/consts/events.py
sgb/consts/facade.py
sgb/consts/file.py
sgb/consts/hosts.py
sgb/consts/names.py
sgb/consts/password.py
sgb/consts/paths.py
sgb/consts/python.py
sgb/consts/recognize.py
sgb/consts/rpc.py
sgb/consts/server_role.py
sgb/consts/settings.py
sgb/consts/style.py
sgb/consts/telephone.py
sgb/consts/zabbix.py
sgb/rpc/__init__.py
sgb/rpc/rpcCommandCall_pb2.py
sgb/rpc/rpcCommandCall_pb2_grpc.py
sgb/service/client.py
sgb/service/collections.py
sgb/service/consts.py
sgb/service/interface/__init__.py
sgb/service/interface/ad.py
sgb/service/interface/dameware.py
sgb/service/interface/executor.py
sgb/service/interface/file.py
sgb/service/interface/password.py
sgb/service/interface/skype.py
sgb/service/interface/ssh.py
sgb/tools/__init__.py
sgb/tools/service.py
sgb-0.124.dist-info/METADATA
sgb-0.124.dist-info/WHEEL
sgb-0.124.dist-info/top_level.txt
sgb-0.124.dist-info/RECORD
